SRLR/__init__.py
SRLR/asymptotics.py
SRLR/datasets.py
SRLR/estimators.py
SRLR/optimal_m.py
SRLR/simulation.py
SRLR/utils.py
SRLR-0.1.8.dist-info/LICENSE
SRLR-0.1.8.dist-info/METADATA
SRLR-0.1.8.dist-info/WHEEL
SRLR-0.1.8.dist-info/top_level.txt
SRLR-0.1.8.dist-info/RECORD
