Metadata-Version: 2.1
Name: SRLR
Version: 0.1.8
Summary: A package for sketched ridgeless estimator simulations, optimizing generalization. Identify the best sketching size to minimize out-of-sample risks. Stable risk curves in optimally sketched estimator eliminate peaks found in full-sample estimator. SRLR offers practical method to discover the ideal sketching size.
Home-page: https://github.com/statsle/SRLR_python
Author: Siyue Yang
Author-email: syue.yang@mail.utoronto.ca
License: MIT
Keywords: python,sketched ridgeless linear regression
Platform: UNKNOWN
Classifier: Programming Language :: Python :: 3
Classifier: Operating System :: MacOS :: MacOS X
Classifier: Operating System :: Microsoft :: Windows
Classifier: Operating System :: POSIX :: Linux
Requires-Python: >=3.6
License-File: LICENSE
Requires-Dist: numpy (>=1.21)
Requires-Dist: scipy (>=1.7)
Requires-Dist: joblib (>=1.3)
Requires-Dist: scikit-learn (>=1.0)
Requires-Dist: matplotlib (>=3.2)
Requires-Dist: scienceplots (>=2.1)
